altinn3_error_handler/__init__.py
altinn3_error_handler/error_handler.py
altinn3_error_handler/requirements.txt
altinn3_error_handler/strategies/__init__.py
altinn3_error_handler/strategies/custom_strategy_template
altinn3_error_handler/strategies/default_handling_strategy.py
altinn3_error_handler/strategies/error_handling_strategy.py
altinn3_error_handler/strategies/http_error_strategy.py
altinn3_error_handler/strategies/retry_strategy.py
altinn3_error_handler/strategies/strategy_invoke_result.py
altinn3_error_handler-0.0.2.dist-info/METADATA
altinn3_error_handler-0.0.2.dist-info/WHEEL
altinn3_error_handler-0.0.2.dist-info/licenses/LICENSE
altinn3_error_handler-0.0.2.dist-info/RECORD
