Metadata-Version: 2.1
Name: altinn3-error-handler
Version: 0.0.2
Summary: A simple framework for customized error handling
Author-email: Anders Hagen <nhk@ssb.no>
License-File: LICENSE
Classifier: License :: OSI Approved :: MIT License
Classifier: Operating System :: OS Independent
Classifier: Programming Language :: Python :: 3
Requires-Python: >=3.9
